Workbook

Sheet 📋 Trade Log
A1: PRO TRADING JOURNAL
A2: Trade Log — Record every trade
A4: Trade # | B4: Date | C4: Market | D4: Symbol | E4: Direction | F4: Setup/Strategy | G4: Entry Price | H4: Stop Loss | I4: Take Profit | J4: Position Size | K4: Exit Price | L4: Exit Date | M4: P&L ($) | N4: P&L (%) | O4: R-Multiple | P4: Commission | Q4: Net P&L ($) | R4: Mistakes | S4: Notes | T4: Screenshot Link
A5: 1 | B5: 2026-05-05 | C5: US | D5: NVDA | E5: Long | F5: Breakout Pullback | G5: 128.5 | H5: 125 | I5: 138 | J5: 100 | K5: 136.2 | L5: 2026-05-06 | M5: 770 | N5: 0.06 | O5: 2.2 | P5: 1.5 | Q5: 768.5 | R5: Entered 10min early | S5: Clean breakout, held well
A6: 2 | B6: 2026-05-06 | C6: HK | D6: 0700.HK | E6: Long | F6: Support Bounce | G6: 512 | H6: 505 | I6: 530 | J6: 200 | K6: 508 | L6: 2026-05-06 | M6: -800 | N6: -0.0078 | O6: -0.57 | P6: 3 | Q6: -803 | R6: No confirmation | S6: Weak bounce, should have waited
A7: 3 | B7: 2026-05-07 | C7: US | D7: TSLA | E7: Short | F7: Bear Flag | G7: 312 | H7: 318 | I7: 295 | J7: 50 | K7: 298.5 | L7: 2026-05-08 | M7: 675 | N7: 0.0433 | O7: 2.25 | P7: 1 | Q7: 674 | S7: Textbook bear flag
A8: 4 | B8: 2026-05-08 | C8: FX | D8: XAUUSD | E8: Long | F8: Trend Following | G8: 3280 | H8: 3260 | I8: 3320 | J8: 1 | K8: 3310 | L8: 2026-05-09 | M8: 30 | N8: 0.0091 | O8: 1.5 | P8: 2 | Q8: 28 | S8: Gold trending up
A9: 5 | B9: 2026-05-09 | C9: A | D9: 600519.SS | E9: Long | F9: Earnings Play | G9: 1850 | H9: 1820 | I9: 1920 | J9: 100 | P9: 5 | S9: Holding - earnings tomorrow
M10: =IF(OR(K10="",(E10="Long")*(K10-G10)*J10,(E10="Short")*(G10-K10)*J10)) | N10: =IF(G10=0,"",M10/(G10*J10)) | O10: =IF(OR(G10=H10,J10=0),"",M10/(ABS(G10-H10)*J10)) | Q10: =IF(M10="","",M10-P10)
M11: =IF(OR(K11="",(E11="Long")*(K11-G11)*J11,(E11="Short")*(G11-K11)*J11)) | N11: =IF(G11=0,"",M11/(G11*J11)) | O11: =IF(OR(G11=H11,J11=0),"",M11/(ABS(G11-H11)*J11)) | Q11: =IF(M11="","",M11-P11)
M12: =IF(OR(K12="",(E12="Long")*(K12-G12)*J12,(E12="Short")*(G12-K12)*J12)) | N12: =IF(G12=0,"",M12/(G12*J12)) | O12: =IF(OR(G12=H12,J12=0),"",M12/(ABS(G12-H12)*J12)) | Q12: =IF(M12="","",M12-P12)
M13: =IF(OR(K13="",(E13="Long")*(K13-G13)*J13,(E13="Short")*(G13-K13)*J13)) | N13: =IF(G13=0,"",M13/(G13*J13)) | O13: =IF(OR(G13=H13,J13=0),"",M13/(ABS(G13-H13)*J13)) | Q13: =IF(M13="","",M13-P13)
M14: =IF(OR(K14="",(E14="Long")*(K14-G14)*J14,(E14="Short")*(G14-K14)*J14)) | N14: =IF(G14=0,"",M14/(G14*J14)) | O14: =IF(OR(G14=H14,J14=0),"",M14/(ABS(G14-H14)*J14)) | Q14: =IF(M14="","",M14-P14)
M15: =IF(OR(K15="",(E15="Long")*(K15-G15)*J15,(E15="Short")*(G15-K15)*J15)) | N15: =IF(G15=0,"",M15/(G15*J15)) | O15: =IF(OR(G15=H15,J15=0),"",M15/(ABS(G15-H15)*J15)) | Q15: =IF(M15="","",M15-P15)
M16: =IF(OR(K16="",(E16="Long")*(K16-G16)*J16,(E16="Short")*(G16-K16)*J16)) | N16: =IF(G16=0,"",M16/(G16*J16)) | O16: =IF(OR(G16=H16,J16=0),"",M16/(ABS(G16-H16)*J16)) | Q16: =IF(M16="","",M16-P16)
M17: =IF(OR(K17="",(E17="Long")*(K17-G17)*J17,(E17="Short")*(G17-K17)*J17)) | N17: =IF(G17=0,"",M17/(G17*J17)) | O17: =IF(OR(G17=H17,J17=0),"",M17/(ABS(G17-H17)*J17)) | Q17: =IF(M17="","",M17-P17)
M18: =IF(OR(K18="",(E18="Long")*(K18-G18)*J18,(E18="Short")*(G18-K18)*J18)) | N18: =IF(G18=0,"",M18/(G18*J18)) | O18: =IF(OR(G18=H18,J18=0),"",M18/(ABS(G18-H18)*J18)) | Q18: =IF(M18="","",M18-P18)
M19: =IF(OR(K19="",(E19="Long")*(K19-G19)*J19,(E19="Short")*(G19-K19)*J19)) | N19: =IF(G19=0,"",M19/(G19*J19)) | O19: =IF(OR(G19=H19,J19=0),"",M19/(ABS(G19-H19)*J19)) | Q19: =IF(M19="","",M19-P19)
M20: =IF(OR(K20="",(E20="Long")*(K20-G20)*J20,(E20="Short")*(G20-K20)*J20)) | N20: =IF(G20=0,"",M20/(G20*J20)) | O20: =IF(OR(G20=H20,J20=0),"",M20/(ABS(G20-H20)*J20)) | Q20: =IF(M20="","",M20-P20)
M21: =IF(OR(K21="",(E21="Long")*(K21-G21)*J21,(E21="Short")*(G21-K21)*J21)) | N21: =IF(G21=0,"",M21/(G21*J21)) | O21: =IF(OR(G21=H21,J21=0),"",M21/(ABS(G21-H21)*J21)) | Q21: =IF(M21="","",M21-P21)
... M23: =IF(OR(K23="",(E23="Long")*(K23-G23)*J23,(E23="Short")*(G23-K23)*J23)) | N23: =IF(G23=0,"",M23/(G23*J23)) | O23: =IF(OR(G23=H23,J23=0),"",M23/(ABS(G23-H23)*J23)) | Q23: =IF(M23="","",M23-P23)

Sheet 📊 Dashboard
A1: TRADING DASHBOARD
A2: Real-time performance overview
A4: TOTAL TRADES | B4: =COUNTA('📋 Trade Log'!A5:A1000)-COUNTBLANK('📋 Trade Log'!A5:A1000) | C4: WIN RATE | D4: =IF(COUNTIF('📋 Trade Log'!M5:M1000,">0")+COUNTIF('📋 Trade Log'!M5:M1000,"<0")=0,"N/A",COUNTIF('📋 Trade Log'!M5:M1000,">0")/(COUNTIF('📋 Trade Log'!M5:M1000,">0")+COUNTIF('📋 Trade Log'!M5:M1000,"<0")))
A5: WINNING TRADES | B5: =COUNTIF('📋 Trade Log'!M5:M1000,">0") | C5: LOSING TRADES | D5: =COUNTIF('📋 Trade Log'!M5:M1000,"<0")
A6: GROSS P&L | B6: =SUM('📋 Trade Log'!M5:M1000) | C6: NET P&L | D6: =SUM('📋 Trade Log'!Q5:Q1000)
A7: AVG WIN | B7: =IF(COUNTIF('📋 Trade Log'!M5:M1000,">0")=0,0,AVERAGEIF('📋 Trade Log'!M5:M1000,">0")) | C7: AVG LOSS | D7: =IF(COUNTIF('📋 Trade Log'!M5:M1000,"<0")=0,0,AVERAGEIF('📋 Trade Log'!M5:M1000,"<0"))
A8: PROFIT FACTOR | B8: =IF(SUMIF('📋 Trade Log'!M5:M1000,"<0")=0,"N/A",-SUMIF('📋 Trade Log'!M5:M1000,">0")/SUMIF('📋 Trade Log'!M5:M1000,"<0")) | C8: AVG R-MULTIPLE | D8: =IF(COUNTA('📋 Trade Log'!O5:O1000)=0,"N/A",AVERAGE('📋 Trade Log'!O5:O1000))
A9: BEST TRADE | B9: =IF(COUNTIF('📋 Trade Log'!M5:M1000,">0")=0,0,MAX('📋 Trade Log'!M5:M1000)) | C9: WORST TRADE | D9: =IF(COUNTIF('📋 Trade Log'!M5:M1000,"<0")=0,0,MIN('📋 Trade Log'!M5:M1000))
A10: AVG HOLD (DAYS) | B10: =IF(COUNTA('📋 Trade Log'!L5:L1000)=0,"N/A",AVERAGE('📋 Trade Log'!L5:L1000-'📋 Trade Log'!B5:B1000)) | C10: COMMISSION TOTAL | D10: =SUM('📋 Trade Log'!P5:P1000)
A11: CURRENT STREAK | C11: MAX DRAWDOWN | D11: =MIN('📋 Trade Log'!M5:M1000)
A14: PERFORMANCE BY MARKET
A15: Market | B15: Trades | C15: Win Rate | D15: Net P&L | E15: Avg R
A16: US | B16: =COUNTIF('📋 Trade Log'!C5:C1000,"US") | C16: =IF(B16=0,"N/A",COUNTIFS('📋 Trade Log'!C5:C1000,"US",'📋 Trade Log'!M5:M1000,">0")/B16) | D16: =SUMIF('📋 Trade Log'!C5:C1000,"US",'📋 Trade Log'!Q5:Q1000) | E16: =IF(B16=0,"N/A",AVERAGEIF('📋 Trade Log'!C5:C1000,"US",'📋 Trade Log'!O5:O1000))
A17: HK | B17: =COUNTIF('📋 Trade Log'!C5:C1000,"HK") | C17: =IF(B17=0,"N/A",COUNTIFS('📋 Trade Log'!C5:C1000,"HK",'📋 Trade Log'!M5:M1000,">0")/B17) | D17: =SUMIF('📋 Trade Log'!C5:C1000,"HK",'📋 Trade Log'!Q5:Q1000) | E17: =IF(B17=0,"N/A",AVERAGEIF('📋 Trade Log'!C5:C1000,"HK",'📋 Trade Log'!O5:O1000))
A18: A | B18: =COUNTIF('📋 Trade Log'!C5:C1000,"A") | C18: =IF(B18=0,"N/A",COUNTIFS('📋 Trade Log'!C5:C1000,"A",'📋 Trade Log'!M5:M1000,">0")/B18) | D18: =SUMIF('📋 Trade Log'!C5:C1000,"A",'📋 Trade Log'!Q5:Q1000) | E18: =IF(B18=0,"N/A",AVERAGEIF('📋 Trade Log'!C5:C1000,"A",'📋 Trade Log'!O5:O1000))
A19: FX | B19: =COUNTIF('📋 Trade Log'!C5:C1000,"FX") | C19: =IF(B19=0,"N/A",COUNTIFS('📋 Trade Log'!C5:C1000,"FX",'📋 Trade Log'!M5:M1000,">0")/B19) | D19: =SUMIF('📋 Trade Log'!C5:C1000,"FX",'📋 Trade Log'!Q5:Q1000) | E19: =IF(B19=0,"N/A",AVERAGEIF('📋 Trade Log'!C5:C1000,"FX",'📋 Trade Log'!O5:O1000))
A20: Crypto | B20: =COUNTIF('📋 Trade Log'!C5:C1000,"Crypto") | C20: =IF(B20=0,"N/A",COUNTIFS('📋 Trade Log'!C5:C1000,"Crypto",'📋 Trade Log'!M5:M1000,">0")/B20) | D20: =SUMIF('📋 Trade Log'!C5:C1000,"Crypto",'📋 Trade Log'!Q5:Q1000) | E20: =IF(B20=0,"N/A",AVERAGEIF('📋 Trade Log'!C5:C1000,"Crypto",'📋 Trade Log'!O5:O1000))
A23: PERFORMANCE BY STRATEGY
A24: Strategy | B24: Trades | C24: Win Rate | D24: Net P&L | E24: Avg R
A25: =IFERROR(INDEX('📋 Trade Log'!F5:F1000,SMALL(IF('📋 Trade Log'!F5:F1000<>"",ROW(F5:F1000)-ROW(F5)+1),1)),"") | B25: =IF(A25="",0,COUNTIF('📋 Trade Log'!F5:F1000,A25)) | C25: =IF(B25=0,"N/A",COUNTIFS('📋 Trade Log'!F5:F1000,A25,'📋 Trade Log'!M5:M1000,">0")/B25) | D25: =IF(A25="","",SUMIF('📋 Trade Log'!F5:F1000,A25,'📋 Trade Log'!Q5:Q1000)) | E25: =IF(A25="","",AVERAGEIF('📋 Trade Log'!F5:F1000,A25,'📋 Trade Log'!O5:O1000))
A26: =IFERROR(INDEX('📋 Trade Log'!F5:F1000,SMALL(IF('📋 Trade Log'!F5:F1000<>"",ROW(F5:F1000)-ROW(F5)+1),2)),"") | B26: =IF(A26="",0,COUNTIF('📋 Trade Log'!F5:F1000,A26)) | C26: =IF(B26=0,"N/A",COUNTIFS('📋 Trade Log'!F5:F1000,A26,'📋 Trade Log'!M5:M1000,">0")/B26) | D26: =IF(A26="","",SUMIF('📋 Trade Log'!F5:F1000,A26,'📋 Trade Log'!Q5:Q1000)) | E26: =IF(A26="","",AVERAGEIF('📋 Trade Log'!F5:F1000,A26,'📋 Trade Log'!O5:O1000))
A27: =IFERROR(INDEX('📋 Trade Log'!F5:F1000,SMALL(IF('📋 Trade Log'!F5:F1000<>"",ROW(F5:F1000)-ROW(F5)+1),3)),"") | B27: =IF(A27="",0,COUNTIF('📋 Trade Log'!F5:F1000,A27)) | C27: =IF(B27=0,"N/A",COUNTIFS('📋 Trade Log'!F5:F1000,A27,'📋 Trade Log'!M5:M1000,">0")/B27) | D27: =IF(A27="","",SUMIF('📋 Trade Log'!F5:F1000,A27,'📋 Trade Log'!Q5:Q1000)) | E27: =IF(A27="","",AVERAGEIF('📋 Trade Log'!F5:F1000,A27,'📋 Trade Log'!O5:O1000))
A28: =IFERROR(INDEX('📋 Trade Log'!F5:F1000,SMALL(IF('📋 Trade Log'!F5:F1000<>"",ROW(F5:F1000)-ROW(F5)+1),4)),"") | B28: =IF(A28="",0,COUNTIF('📋 Trade Log'!F5:F1000,A28)) | C28: =IF(B28=0,"N/A",COUNTIFS('📋 Trade Log'!F5:F1000,A28,'📋 Trade Log'!M5:M1000,">0")/B28) | D28: =IF(A28="","",SUMIF('📋 Trade Log'!F5:F1000,A28,'📋 Trade Log'!Q5:Q1000)) | E28: =IF(A28="","",AVERAGEIF('📋 Trade Log'!F5:F1000,A28,'📋 Trade Log'!O5:O1000))
A29: =IFERROR(INDEX('📋 Trade Log'!F5:F1000,SMALL(IF('📋 Trade Log'!F5:F1000<>"",ROW(F5:F1000)-ROW(F5)+1),5)),"") | B29: =IF(A29="",0,COUNTIF('📋 Trade Log'!F5:F1000,A29)) | C29: =IF(B29=0,"N/A",COUNTIFS('📋 Trade Log'!F5:F1000,A29,'📋 Trade Log'!M5:M1000,">0")/B29) | D29: =IF(A29="","",SUMIF('📋 Trade Log'!F5:F1000,A29,'📋 Trade Log'!Q5:Q1000)) | E29: =IF(A29="","",AVERAGEIF('📋 Trade Log'!F5:F1000,A29,'📋 Trade Log'!O5:O1000))

Sheet 📈 Analytics
A1: TRADING ANALYTICS
A2: Deep performance analysis
A4: CUMULATIVE P&L (by trade) | G4: WIN/LOSS DISTRIBUTION
A5: Trade # | B5: Date | C5: Net P&L | D5: Cumulative P&L | G5: Range | H5: Count | I5: %
A6: 1 | B6: =INDEX('📋 Trade Log'!B5:B1000,1) | C6: =INDEX('📋 Trade Log'!Q5:Q1000,1) | D6: =C6 | G6: > $500 | H6: =COUNTIF('📋 Trade Log'!Q5:Q1000,">500") | I6: =IF(SUM($H$6:$H$11)=0,"",H6/SUM($H$6:$H$11))
A7: 2 | B7: =INDEX('📋 Trade Log'!B5:B1000,2) | C7: =INDEX('📋 Trade Log'!Q5:Q1000,2) | D7: =D6+C7 | G7: $100 - $500 | H7: =COUNTIFS('📋 Trade Log'!Q5:Q1000,">=100",'📋 Trade Log'!Q5:Q1000,"<=500") | I7: =IF(SUM($H$6:$H$11)=0,"",H7/SUM($H$6:$H$11))
A8: 3 | B8: =INDEX('📋 Trade Log'!B5:B1000,3) | C8: =INDEX('📋 Trade Log'!Q5:Q1000,3) | D8: =D7+C8 | G8: $0 - $100 | H8: =COUNTIFS('📋 Trade Log'!Q5:Q1000,">=0",'📋 Trade Log'!Q5:Q1000,"<100") | I8: =IF(SUM($H$6:$H$11)=0,"",H8/SUM($H$6:$H$11))
A9: 4 | B9: =INDEX('📋 Trade Log'!B5:B1000,4) | C9: =INDEX('📋 Trade Log'!Q5:Q1000,4) | D9: =D8+C9 | G9: -$100 - $0 | H9: =COUNTIFS('📋 Trade Log'!Q5:Q1000,">=-100",'📋 Trade Log'!Q5:Q1000,"<0") | I9: =IF(SUM($H$6:$H$11)=0,"",H9/SUM($H$6:$H$11))
A10: 5 | B10: =INDEX('📋 Trade Log'!B5:B1000,5) | C10: =INDEX('📋 Trade Log'!Q5:Q1000,5) | D10: =D9+C10 | G10: -$500 - -$100 | H10: =COUNTIFS('📋 Trade Log'!Q5:Q1000,">=-500",'📋 Trade Log'!Q5:Q1000,"<-100") | I10: =IF(SUM($H$6:$H$11)=0,"",H10/SUM($H$6:$H$11))
A11: 6 | B11: =INDEX('📋 Trade Log'!B5:B1000,6) | C11: =INDEX('📋 Trade Log'!Q5:Q1000,6) | D11: =D10+C11 | G11: < -$500 | H11: =COUNTIF('📋 Trade Log'!Q5:Q1000,"<-500") | I11: =IF(SUM($H$6:$H$11)=0,"",H11/SUM($H$6:$H$11))
A12: 7 | B12: =INDEX('📋 Trade Log'!B5:B1000,7) | C12: =INDEX('📋 Trade Log'!Q5:Q1000,7) | D12: =D11+C12
A13: 8 | B13: =INDEX('📋 Trade Log'!B5:B1000,8) | C13: =INDEX('📋 Trade Log'!Q5:Q1000,8) | D13: =D12+C13
A14: MONTHLY PERFORMANCE | B14: =INDEX('📋 Trade Log'!B5:B1000,9) | C14: =INDEX('📋 Trade Log'!Q5:Q1000,9) | D14: =D13+C14
A15: Month | B15: Trades | C15: Win Rate | D15: Gross P&L | E15: Net P&L | F15: Avg R
A16: Jan | B16: =COUNTIFS('📋 Trade Log'!B5:B1000,">=2026-01-01",'📋 Trade Log'!B5:B1000,"<2026-02-01") | C16: =IF(B16=0,"N/A",COUNTIFS('📋 Trade Log'!B5:B1000,">=2026-01-01",'📋 Trade Log'!B5:B1000,"<2026-02-01",'📋 Trade Log'!M5:M1000,">0")/B16) | D16: =SUMIFS('📋 Trade Log'!M5:M1000,'📋 Trade Log'!B5:B1000,">=2026-01-01",'📋 Trade Log'!B5:B1000,"<2026-02-01") | E16: =SUMIFS('📋 Trade Log'!Q5:Q1000,'📋 Trade Log'!B5:B1000,">=2026-01-01",'📋 Trade Log'!B5:B1000,"<2026-02-01") | F16: =IF(B16=0,"N/A",AVERAGEIFS('📋 Trade Log'!O5:O1000,'📋 Trade Log'!B5:B1000,">=2026-01-01",'📋 Trade Log'!B5:B1000,"<2026-02-01"))
A17: Feb | B17: =COUNTIFS('📋 Trade Log'!B5:B1000,">=2026-02-01",'📋 Trade Log'!B5:B1000,"<2026-03-01") | C17: =IF(B17=0,"N/A",COUNTIFS('📋 Trade Log'!B5:B1000,">=2026-02-01",'📋 Trade Log'!B5:B1000,"<2026-03-01",'📋 Trade Log'!M5:M1000,">0")/B17) | D17: =SUMIFS('📋 Trade Log'!M5:M1000,'📋 Trade Log'!B5:B1000,">=2026-02-01",'📋 Trade Log'!B5:B1000,"<2026-03-01") | E17: =SUMIFS('📋 Trade Log'!Q5:Q1000,'📋 Trade Log'!B5:B1000,">=2026-02-01",'📋 Trade Log'!B5:B1000,"<2026-03-01") | F17: =IF(B17=0,"N/A",AVERAGEIFS('📋 Trade Log'!O5:O1000,'📋 Trade Log'!B5:B1000,">=2026-02-01",'📋 Trade Log'!B5:B1000,"<2026-03-01"))
A18: Mar | B18: =COUNTIFS('📋 Trade Log'!B5:B1000,">=2026-03-01",'📋 Trade Log'!B5:B1000,"<2026-04-01") | C18: =IF(B18=0,"N/A",COUNTIFS('📋 Trade Log'!B5:B1000,">=2026-03-01",'📋 Trade Log'!B5:B1000,"<2026-04-01",'📋 Trade Log'!M5:M1000,">0")/B18) | D18: =SUMIFS('📋 Trade Log'!M5:M1000,'📋 Trade Log'!B5:B1000,">=2026-03-01",'📋 Trade Log'!B5:B1000,"<2026-04-01") | E18: =SUMIFS('📋 Trade Log'!Q5:Q1000,'📋 Trade Log'!B5:B1000,">=2026-03-01",'📋 Trade Log'!B5:B1000,"<2026-04-01") | F18: =IF(B18=0,"N/A",AVERAGEIFS('📋 Trade Log'!O5:O1000,'📋 Trade Log'!B5:B1000,">=2026-03-01",'📋 Trade Log'!B5:B1000,"<2026-04-01"))
A19: Apr | B19: =COUNTIFS('📋 Trade Log'!B5:B1000,">=2026-04-01",'📋 Trade Log'!B5:B1000,"<2026-05-01") | C19: =IF(B19=0,"N/A",COUNTIFS('📋 Trade Log'!B5:B1000,">=2026-04-01",'📋 Trade Log'!B5:B1000,"<2026-05-01",'📋 Trade Log'!M5:M1000,">0")/B19) | D19: =SUMIFS('📋 Trade Log'!M5:M1000,'📋 Trade Log'!B5:B1000,">=2026-04-01",'📋 Trade Log'!B5:B1000,"<2026-05-01") | E19: =SUMIFS('📋 Trade Log'!Q5:Q1000,'📋 Trade Log'!B5:B1000,">=2026-04-01",'📋 Trade Log'!B5:B1000,"<2026-05-01") | F19: =IF(B19=0,"N/A",AVERAGEIFS('📋 Trade Log'!O5:O1000,'📋 Trade Log'!B5:B1000,">=2026-04-01",'📋 Trade Log'!B5:B1000,"<2026-05-01"))
A20: May | B20: =COUNTIFS('📋 Trade Log'!B5:B1000,">=2026-05-01",'📋 Trade Log'!B5:B1000,"<2026-06-01") | C20: =IF(B20=0,"N/A",COUNTIFS('📋 Trade Log'!B5:B1000,">=2026-05-01",'📋 Trade Log'!B5:B1000,"<2026-06-01",'📋 Trade Log'!M5:M1000,">0")/B20) | D20: =SUMIFS('📋 Trade Log'!M5:M1000,'📋 Trade Log'!B5:B1000,">=2026-05-01",'📋 Trade Log'!B5:B1000,"<2026-06-01") | E20: =SUMIFS('📋 Trade Log'!Q5:Q1000,'📋 Trade Log'!B5:B1000,">=2026-05-01",'📋 Trade Log'!B5:B1000,"<2026-06-01") | F20: =IF(B20=0,"N/A",AVERAGEIFS('📋 Trade Log'!O5:O1000,'📋 Trade Log'!B5:B1000,">=2026-05-01",'📋 Trade Log'!B5:B1000,"<2026-06-01"))
A21: Jun | B21: =COUNTIFS('📋 Trade Log'!B5:B1000,">=2026-06-01",'📋 Trade Log'!B5:B1000,"<2026-07-01") | C21: =IF(B21=0,"N/A",COUNTIFS('📋 Trade Log'!B5:B1000,">=2026-06-01",'📋 Trade Log'!B5:B1000,"<2026-07-01",'📋 Trade Log'!M5:M1000,">0")/B21) | D21: =SUMIFS('📋 Trade Log'!M5:M1000,'📋 Trade Log'!B5:B1000,">=2026-06-01",'📋 Trade Log'!B5:B1000,"<2026-07-01") | E21: =SUMIFS('📋 Trade Log'!Q5:Q1000,'📋 Trade Log'!B5:B1000,">=2026-06-01",'📋 Trade Log'!B5:B1000,"<2026-07-01") | F21: =IF(B21=0,"N/A",AVERAGEIFS('📋 Trade Log'!O5:O1000,'📋 Trade Log'!B5:B1000,">=2026-06-01",'📋 Trade Log'!B5:B1000,"<2026-07-01"))
A22: Jul | B22: =COUNTIFS('📋 Trade Log'!B5:B1000,">=2026-07-01",'📋 Trade Log'!B5:B1000,"<2026-08-01") | C22: =IF(B22=0,"N/A",COUNTIFS('📋 Trade Log'!B5:B1000,">=2026-07-01",'📋 Trade Log'!B5:B1000,"<2026-08-01",'📋 Trade Log'!M5:M1000,">0")/B22) | D22: =SUMIFS('📋 Trade Log'!M5:M1000,'📋 Trade Log'!B5:B1000,">=2026-07-01",'📋 Trade Log'!B5:B1000,"<2026-08-01") | E22: =SUMIFS('📋 Trade Log'!Q5:Q1000,'📋 Trade Log'!B5:B1000,">=2026-07-01",'📋 Trade Log'!B5:B1000,"<2026-08-01") | F22: =IF(B22=0,"N/A",AVERAGEIFS('📋 Trade Log'!O5:O1000,'📋 Trade Log'!B5:B1000,">=2026-07-01",'📋 Trade Log'!B5:B1000,"<2026-08-01"))
A23: Aug | B23: =COUNTIFS('📋 Trade Log'!B5:B1000,">=2026-08-01",'📋 Trade Log'!B5:B1000,"<2026-09-01") | C23: =IF(B23=0,"N/A",COUNTIFS('📋 Trade Log'!B5:B1000,">=2026-08-01",'📋 Trade Log'!B5:B1000,"<2026-09-01",'📋 Trade Log'!M5:M1000,">0")/B23) | D23: =SUMIFS('📋 Trade Log'!M5:M1000,'📋 Trade Log'!B5:B1000,">=2026-08-01",'📋 Trade Log'!B5:B1000,"<2026-09-01") | E23: =SUMIFS('📋 Trade Log'!Q5:Q1000,'📋 Trade Log'!B5:B1000,">=2026-08-01",'📋 Trade Log'!B5:B1000,"<2026-09-01") | F23: =IF(B23=0,"N/A",AVERAGEIFS('📋 Trade Log'!O5:O1000,'📋 Trade Log'!B5:B1000,">=2026-08-01",'📋 Trade Log'!B5:B1000,"<2026-09-01"))
A24: Sep | B24: =COUNTIFS('📋 Trade Log'!B5:B1000,">=2026-09-01",'📋 Trade Log'!B5:B1000,"<2026-10-01") | C24: =IF(B24=0,"N/A",COUNTIFS('📋 Trade Log'!B5:B1000,">=2026-09-01",'📋 Trade Log'!B5:B1000,"<2026-10-01",'📋 Trade Log'!M5:M1000,">0")/B24) | D24: =SUMIFS('📋 Trade Log'!M5:M1000,'📋 Trade Log'!B5:B1000,">=2026-09-01",'📋 Trade Log'!B5:B1000,"<2026-10-01") | E24: =SUMIFS('📋 Trade Log'!Q5:Q1000,'📋 Trade Log'!B5:B1000,">=2026-09-01",'📋 Trade Log'!B5:B1000,"<2026-10-01") | F24: =IF(B24=0,"N/A",AVERAGEIFS('📋 Trade Log'!O5:O1000,'📋 Trade Log'!B5:B1000,">=2026-09-01",'📋 Trade Log'!B5:B1000,"<2026-10-01"))
A25: Oct | B25: =COUNTIFS('📋 Trade Log'!B5:B1000,">=2026-10-01",'📋 Trade Log'!B5:B1000,"<2026-11-01") | C25: =IF(B25=0,"N/A",COUNTIFS('📋 Trade Log'!B5:B1000,">=2026-10-01",'📋 Trade Log'!B5:B1000,"<2026-11-01",'📋 Trade Log'!M5:M1000,">0")/B25) | D25: =SUMIFS('📋 Trade Log'!M5:M1000,'📋 Trade Log'!B5:B1000,">=2026-10-01",'📋 Trade Log'!B5:B1000,"<2026-11-01") | E25: =SUMIFS('📋 Trade Log'!Q5:Q1000,'📋 Trade Log'!B5:B1000,">=2026-10-01",'📋 Trade Log'!B5:B1000,"<2026-11-01") | F25: =IF(B25=0,"N/A",AVERAGEIFS('📋 Trade Log'!O5:O1000,'📋 Trade Log'!B5:B1000,">=2026-10-01",'📋 Trade Log'!B5:B1000,"<2026-11-01"))
A26: Nov | B26: =COUNTIFS('📋 Trade Log'!B5:B1000,">=2026-11-01",'📋 Trade Log'!B5:B1000,"<2026-12-01") | C26: =IF(B26=0,"N/A",COUNTIFS('📋 Trade Log'!B5:B1000,">=2026-11-01",'📋 Trade Log'!B5:B1000,"<2026-12-01",'📋 Trade Log'!M5:M1000,">0")/B26) | D26: =SUMIFS('📋 Trade Log'!M5:M1000,'📋 Trade Log'!B5:B1000,">=2026-11-01",'📋 Trade Log'!B5:B1000,"<2026-12-01") | E26: =SUMIFS('📋 Trade Log'!Q5:Q1000,'📋 Trade Log'!B5:B1000,">=2026-11-01",'📋 Trade Log'!B5:B1000,"<2026-12-01") | F26: =IF(B26=0,"N/A",AVERAGEIFS('📋 Trade Log'!O5:O1000,'📋 Trade Log'!B5:B1000,">=2026-11-01",'📋 Trade Log'!B5:B1000,"<2026-12-01"))
A27: Dec | B27: =COUNTIFS('📋 Trade Log'!B5:B1000,">=2026-12-01",'📋 Trade Log'!B5:B1000,"<2026-13-01") | C27: =IF(B27=0,"N/A",COUNTIFS('📋 Trade Log'!B5:B1000,">=2026-12-01",'📋 Trade Log'!B5:B1000,"<2026-13-01",'📋 Trade Log'!M5:M1000,">0")/B27) | D27: =SUMIFS('📋 Trade Log'!M5:M1000,'📋 Trade Log'!B5:B1000,">=2026-12-01",'📋 Trade Log'!B5:B1000,"<2026-13-01") | E27: =SUMIFS('📋 Trade Log'!Q5:Q1000,'📋 Trade Log'!B5:B1000,">=2026-12-01",'📋 Trade Log'!B5:B1000,"<2026-13-01") | F27: =IF(B27=0,"N/A",AVERAGEIFS('📋 Trade Log'!O5:O1000,'📋 Trade Log'!B5:B1000,">=2026-12-01",'📋 Trade Log'!B5:B1000,"<2026-13-01"))

Sheet 📖 How to Use
A1: PRO TRADING JOURNAL
A2: Setup Guide & Instructions
A4: 🚀 QUICK START
A5: 1. Open this file in Google Sheets (upload to Google Drive, double-click)
A6: 2. Go to the '📋 Trade Log' tab and start entering your trades
A7: 3. The Dashboard and Analytics update automatically
A8: 📋 TRADE LOG — How to Fill In
A9: • Trade #: Auto-numbered (just enter 1, 2, 3...)
A10: • Date: Entry date (YYYY-MM-DD)
A11: • Market: US / HK / A / FX / Crypto
A12: • Symbol: Ticker (e.g., NVDA, 0700.HK, XAUUSD)
A13: • Direction: Long or Short
... A40: • Track every trade — even the small ones — for accurate stats
